<?xml version="1.0" encoding="UTF-8"?>
<objects serializationModel="Studio.02.02.00">
	<object class="AudioFile" id="{8701c75a-94cd-4745-a593-d6eec1e7c2dc}">
		<property name="assetPath">
			<value>Rani/Convo4_TheseAreNotBeings.wav</value>
		</property>
		<property name="frequencyInKHz">
			<value>48</value>
		</property>
		<property name="channelCount">
			<value>2</value>
		</property>
		<property name="length">
			<value>3.2442916666666668</value>
		</property>
		<relationship name="masterAssetFolder">
			<destination>{01765d1c-b5dd-43f1-ae19-5c000a75f99d}</destination>
		</relationship>
	</object>
</objects>
